memoize/__init__.py
python_memoize-1.0.0.dist-info/LICENSE
python_memoize-1.0.0.dist-info/METADATA
python_memoize-1.0.0.dist-info/WHEEL
python_memoize-1.0.0.dist-info/top_level.txt
python_memoize-1.0.0.dist-info/RECORD
